{
  "pop":[
    {
      "page":1,
      "list": [
        {
          "title":"Flowers",
          "imageUrl":"https://dummyimage.com/150X200 ",
          "id": 1
        },
        {
          "title":"Flowers",
          "imageUrl":"https://dummyimage.com/150X200 ",
          "id": 2
        },
        {
          "title":"Flowers",
          "imageUrl":"https://dummyimage.com/150X200 ",
          "id": 3
        },
        {
          "title":"Flowers",
          "imageUrl":"https://dummyimage.com/150X200 ",
          "id": 4
        },
        {
          "title":"Flowers",
          "imageUrl":"https://dummyimage.com/150X200 ",
          "id": 5
        },
        {
          "title":"Flowers",
          "imageUrl":"https://dummyimage.com/150X200 ",
          "id": 6
        },
        {
          "title":"Flowers",
          "imageUrl":"https://dummyimage.com/150X200 ",
          "id": 7
        },
        {
          "title":"Flowers",
          "imageUrl":"https://dummyimage.com/150X200 ",
          "id": 8
        },
        {
          "title":"Flowers",
          "imageUrl":"https://dummyimage.com/150X200 ",
          "id": 9
        },
        {
          "title":"Flowers",
          "imageUrl":"https://dummyimage.com/150X200 ",
          "id": 10
        }
      ]
    },
    {
      "page":2,
      "list": [
        {
          "title":"Flowers",
          "imageUrl":"https://dummyimage.com/150X200 ",
          "id": 11
        },
        {
          "title":"Flowers",
          "imageUrl":"https://dummyimage.com/150X200 ",
          "id": 12
        },
        {
          "title":"Flowers",
          "imageUrl":"https://dummyimage.com/150X200 ",
          "id": 13
        },
        {
          "title":"Flowers",
          "imageUrl":"https://dummyimage.com/150X200 ",
          "id": 14
        },
        {
          "title":"Flowers",
          "imageUrl":"https://dummyimage.com/150X200 ",
          "id": 15
        },
        {
          "title":"Flowers",
          "imageUrl":"https://dummyimage.com/150X200 ",
          "id": 16
        },
        {
          "title":"Flowers",
          "imageUrl":"https://dummyimage.com/150X200 ",
          "id": 17
        },
        {
          "title":"Flowers",
          "imageUrl":"https://dummyimage.com/150X200 ",
          "id": 18
        },
        {
          "title":"Flowers",
          "imageUrl":"https://dummyimage.com/150X200 ",
          "id": 19
        },
        {
          "title":"Flowers",
          "imageUrl":"https://dummyimage.com/150X200 ",
          "id": 20
        }
      ]
    },
    {
      "page":3,
      "list": [
        {
          "title":"Flowers",
          "imageUrl":"https://dummyimage.com/150X200 ",
          "id": 21
        },
        {
          "title":"Flowers",
          "imageUrl":"https://dummyimage.com/150X200 ",
          "id": 22
        },
        {
          "title":"Flowers",
          "imageUrl":"https://dummyimage.com/150X200 ",
          "id": 23
        },
        {
          "title":"Flowers",
          "imageUrl":"https://dummyimage.com/150X200 ",
          "id": 24
        },
        {
          "title":"Flowers",
          "imageUrl":"https://dummyimage.com/150X200 ",
          "id": 25
        },
        {
          "title":"Flowers",
          "imageUrl":"https://dummyimage.com/150X200 ",
          "id": 26
        },
        {
          "title":"Flowers",
          "imageUrl":"https://dummyimage.com/150X200 ",
          "id": 27
        },
        {
          "title":"Flowers",
          "imageUrl":"https://dummyimage.com/150X200 ",
          "id": 28
        },
        {
          "title":"Flowers",
          "imageUrl":"https://dummyimage.com/150X200 ",
          "id": 29
        },
        {
          "title":"Flowers",
          "imageUrl":"https://dummyimage.com/150X200 ",
          "id": 30
        }
      ]
    },
    {
      "page":4,
      "list": [
        {
          "title":"Flowers",
          "imageUrl":"https://dummyimage.com/150X200 ",
          "id": 31
        },
        {
          "title":"Flowers",
          "imageUrl":"https://dummyimage.com/150X200 ",
          "id": 32
        },
        {
          "title":"Flowers",
          "imageUrl":"https://dummyimage.com/150X200 ",
          "id": 33
        },
        {
          "title":"Flowers",
          "imageUrl":"https://dummyimage.com/150X200 ",
          "id": 34
        },
        {
          "title":"Flowers",
          "imageUrl":"https://dummyimage.com/150X200 ",
          "id": 35
        },
        {
          "title":"Flowers",
          "imageUrl":"https://dummyimage.com/150X200 ",
          "id": 36
        },
        {
          "title":"Flowers",
          "imageUrl":"https://dummyimage.com/150X200 ",
          "id": 37
        },
        {
          "title":"Flowers",
          "imageUrl":"https://dummyimage.com/150X200 ",
          "id": 38
        },
        {
          "title":"Flowers",
          "imageUrl":"https://dummyimage.com/150X200 ",
          "id": 39
        },
        {
          "title":"Flowers",
          "imageUrl":"https://dummyimage.com/150X200 ",
          "id": 40
        }
      ]
    },
    {
      "page":5,
      "list": [
        {
          "title":"Flowers",
          "imageUrl":"https://dummyimage.com/150X200 ",
          "id": 41
        },
        {
          "title":"Flowers",
          "imageUrl":"https://dummyimage.com/150X200 ",
          "id": 42
        },
        {
          "title":"Flowers",
          "imageUrl":"https://dummyimage.com/150X200 ",
          "id": 43
        },
        {
          "title":"Flowers",
          "imageUrl":"https://dummyimage.com/150X200 ",
          "id": 44
        },
        {
          "title":"Flowers",
          "imageUrl":"https://dummyimage.com/150X200 ",
          "id": 45
        },
        {
          "title":"Flowers",
          "imageUrl":"https://dummyimage.com/150X200 ",
          "id": 46
        },
        {
          "title":"Flowers",
          "imageUrl":"https://dummyimage.com/150X200 ",
          "id": 47
        },
        {
          "title":"Flowers",
          "imageUrl":"https://dummyimage.com/150X200 ",
          "id": 48
        },
        {
          "title":"Flowers",
          "imageUrl":"https://dummyimage.com/150X200 ",
          "id": 49
        },
        {
          "title":"Flowers",
          "imageUrl":"https://dummyimage.com/150X200 ",
          "id": 50
        }
      ]
    }
  ],
  "sell":[
    {
      "page":1,
      "list": [
        {
          "title":"Flowers",
          "imageUrl":"https://dummyimage.com/150X200 ",
          "id": 1
        },
        {
          "title":"Flowers",
          "imageUrl":"https://dummyimage.com/150X200 ",
          "id": 2
        },
        {
          "title":"Flowers",
          "imageUrl":"https://dummyimage.com/150X200 ",
          "id": 3
        },
        {
          "title":"Flowers",
          "imageUrl":"https://dummyimage.com/150X200 ",
          "id": 4
        },
        {
          "title":"Flowers",
          "imageUrl":"https://dummyimage.com/150X200 ",
          "id": 5
        },
        {
          "title":"Flowers",
          "imageUrl":"https://dummyimage.com/150X200 ",
          "id": 6
        },
        {
          "title":"Flowers",
          "imageUrl":"https://dummyimage.com/150X200 ",
          "id": 7
        },
        {
          "title":"Flowers",
          "imageUrl":"https://dummyimage.com/150X200 ",
          "id": 8
        },
        {
          "title":"Flowers",
          "imageUrl":"https://dummyimage.com/150X200 ",
          "id": 9
        },
        {
          "title":"Flowers",
          "imageUrl":"https://dummyimage.com/150X200 ",
          "id": 10
        }
      ]
    },
    {
      "page":2,
      "list": [
        {
          "title":"sell",
          "imageUrl":"https://dummyimage.com/150X200 "
        },
        {
          "title":"sell",
          "imageUrl":"https://dummyimage.com/150X200 "
        },
        {
          "title":"sell",
          "imageUrl":"https://dummyimage.com/150X200 "
        },
        {
          "title":"sell",
          "imageUrl":"https://dummyimage.com/150X200 "
        },
        {
          "title":"sell",
          "imageUrl":"https://dummyimage.com/150X200 "
        },
        {
          "title":"sell",
          "imageUrl":"https://dummyimage.com/150X200 "
        },
        {
          "title":"sell",
          "imageUrl":"https://dummyimage.com/150X200 "
        },
        {
          "title":"sell",
          "imageUrl":"https://dummyimage.com/150X200 "
        },
        {
          "title":"sell",
          "imageUrl":"https://dummyimage.com/150X200 "
        },
        {
          "title":"sell",
          "imageUrl":"https://dummyimage.com/150X200 "
        }
      ]
    },
    {
      "page":3,
      "list": [
        {
          "title":"sell",
          "imageUrl":"https://dummyimage.com/150X200 "
        },
        {
          "title":"sell",
          "imageUrl":"https://dummyimage.com/150X200 "
        },
        {
          "title":"sell",
          "imageUrl":"https://dummyimage.com/150X200 "
        },
        {
          "title":"sell",
          "imageUrl":"https://dummyimage.com/150X200 "
        },
        {
          "title":"sell",
          "imageUrl":"https://dummyimage.com/150X200 "
        },
        {
          "title":"sell",
          "imageUrl":"https://dummyimage.com/150X200 "
        },
        {
          "title":"sell",
          "imageUrl":"https://dummyimage.com/150X200 "
        },
        {
          "title":"sell",
          "imageUrl":"https://dummyimage.com/150X200 "
        },
        {
          "title":"sell",
          "imageUrl":"https://dummyimage.com/150X200 "
        },
        {
          "title":"sell",
          "imageUrl":"https://dummyimage.com/150X200 "
        }
      ]
    },
    {
      "page":4,
      "list": [
        {
          "title":"sell",
          "imageUrl":"https://dummyimage.com/150X200 "
        },
        {
          "title":"sell",
          "imageUrl":"https://dummyimage.com/150X200 "
        },
        {
          "title":"sell",
          "imageUrl":"https://dummyimage.com/150X200 "
        },
        {
          "title":"sell",
          "imageUrl":"https://dummyimage.com/150X200 "
        },
        {
          "title":"sell",
          "imageUrl":"https://dummyimage.com/150X200 "
        },
        {
          "title":"sell",
          "imageUrl":"https://dummyimage.com/150X200 "
        },
        {
          "title":"sell",
          "imageUrl":"https://dummyimage.com/150X200 "
        },
        {
          "title":"sell",
          "imageUrl":"https://dummyimage.com/150X200 "
        },
        {
          "title":"sell",
          "imageUrl":"https://dummyimage.com/150X200 "
        },
        {
          "title":"sell",
          "imageUrl":"https://dummyimage.com/150X200 "
        }
      ]
    },
    {
      "page":5,
      "list": [
        {
          "title":"sell",
          "imageUrl":"https://dummyimage.com/150X200 "
        },
        {
          "title":"sell",
          "imageUrl":"https://dummyimage.com/150X200 "
        },
        {
          "title":"sell",
          "imageUrl":"https://dummyimage.com/150X200 "
        },
        {
          "title":"sell",
          "imageUrl":"https://dummyimage.com/150X200 "
        },
        {
          "title":"sell",
          "imageUrl":"https://dummyimage.com/150X200 "
        },
        {
          "title":"sell",
          "imageUrl":"https://dummyimage.com/150X200 "
        },
        {
          "title":"sell",
          "imageUrl":"https://dummyimage.com/150X200 "
        },
        {
          "title":"sell",
          "imageUrl":"https://dummyimage.com/150X200 "
        },
        {
          "title":"sell",
          "imageUrl":"https://dummyimage.com/150X200 "
        },
        {
          "title":"sell",
          "imageUrl":"https://dummyimage.com/150X200 "
        }
      ]
    }
  ],
  "news":[
    {
      "page":1,
      "list": [
        {
          "title":"news",
          "imageUrl":"https://dummyimage.com/150X200 "
        },
        {
          "title":"news",
          "imageUrl":"https://dummyimage.com/150X200 "
        },
        {
          "title":"news",
          "imageUrl":"https://dummyimage.com/150X200 "
        },
        {
          "title":"news",
          "imageUrl":"https://dummyimage.com/150X200 "
        },
        {
          "title":"news",
          "imageUrl":"https://dummyimage.com/150X200 "
        },
        {
          "title":"news",
          "imageUrl":"https://dummyimage.com/150X200 "
        },
        {
          "title":"news",
          "imageUrl":"https://dummyimage.com/150X200 "
        },
        {
          "title":"news",
          "imageUrl":"https://dummyimage.com/150X200 "
        },
        {
          "title":"news",
          "imageUrl":"https://dummyimage.com/150X200 "
        },
        {
          "title":"news",
          "imageUrl":"https://dummyimage.com/150X200 "
        }
      ]
    },
    {
      "page":2,
      "list": [
        {
          "title":"news",
          "imageUrl":"https://dummyimage.com/150X200 "
        },
        {
          "title":"news",
          "imageUrl":"https://dummyimage.com/150X200 "
        },
        {
          "title":"news",
          "imageUrl":"https://dummyimage.com/150X200 "
        },
        {
          "title":"news",
          "imageUrl":"https://dummyimage.com/150X200 "
        },
        {
          "title":"news",
          "imageUrl":"https://dummyimage.com/150X200 "
        },
        {
          "title":"news",
          "imageUrl":"https://dummyimage.com/150X200 "
        },
        {
          "title":"news",
          "imageUrl":"https://dummyimage.com/150X200 "
        },
        {
          "title":"news",
          "imageUrl":"https://dummyimage.com/150X200 "
        },
        {
          "title":"news",
          "imageUrl":"https://dummyimage.com/150X200 "
        },
        {
          "title":"news",
          "imageUrl":"https://dummyimage.com/150X200 "
        }
      ]
    },
    {
      "page":3,
      "list": [
        {
          "title":"news",
          "imageUrl":"https://dummyimage.com/150X200 "
        },
        {
          "title":"news",
          "imageUrl":"https://dummyimage.com/150X200 "
        },
        {
          "title":"news",
          "imageUrl":"https://dummyimage.com/150X200 "
        },
        {
          "title":"news",
          "imageUrl":"https://dummyimage.com/150X200 "
        },
        {
          "title":"news",
          "imageUrl":"https://dummyimage.com/150X200 "
        },
        {
          "title":"news",
          "imageUrl":"https://dummyimage.com/150X200 "
        },
        {
          "title":"news",
          "imageUrl":"https://dummyimage.com/150X200 "
        },
        {
          "title":"news",
          "imageUrl":"https://dummyimage.com/150X200 "
        },
        {
          "title":"news",
          "imageUrl":"https://dummyimage.com/150X200 "
        },
        {
          "title":"news",
          "imageUrl":"https://dummyimage.com/150X200 "
        }
      ]
    },
    {
      "page":4,
      "list": [
        {
          "title":"news",
          "imageUrl":"https://dummyimage.com/150X200 "
        },
        {
          "title":"news",
          "imageUrl":"https://dummyimage.com/150X200 "
        },
        {
          "title":"news",
          "imageUrl":"https://dummyimage.com/150X200 "
        },
        {
          "title":"news",
          "imageUrl":"https://dummyimage.com/150X200 "
        },
        {
          "title":"news",
          "imageUrl":"https://dummyimage.com/150X200 "
        },
        {
          "title":"news",
          "imageUrl":"https://dummyimage.com/150X200 "
        },
        {
          "title":"news",
          "imageUrl":"https://dummyimage.com/150X200 "
        },
        {
          "title":"news",
          "imageUrl":"https://dummyimage.com/150X200 "
        },
        {
          "title":"news",
          "imageUrl":"https://dummyimage.com/150X200 "
        },
        {
          "title":"news",
          "imageUrl":"https://dummyimage.com/150X200 "
        }
      ]
    },
    {
      "page":5,
      "list": [
        {
          "title":"news",
          "imageUrl":"https://dummyimage.com/150X200 "
        },
        {
          "title":"news",
          "imageUrl":"https://dummyimage.com/150X200 "
        },
        {
          "title":"news",
          "imageUrl":"https://dummyimage.com/150X200 "
        },
        {
          "title":"news",
          "imageUrl":"https://dummyimage.com/150X200 "
        },
        {
          "title":"news",
          "imageUrl":"https://dummyimage.com/150X200 "
        },
        {
          "title":"news",
          "imageUrl":"https://dummyimage.com/150X200 "
        },
        {
          "title":"news",
          "imageUrl":"https://dummyimage.com/150X200 "
        },
        {
          "title":"news",
          "imageUrl":"https://dummyimage.com/150X200 "
        },
        {
          "title":"news",
          "imageUrl":"https://dummyimage.com/150X200 "
        },
        {
          "title":"news",
          "imageUrl":"https://dummyimage.com/150X200 "
        }
      ]
    }
  ]
}
